ezm_agent/__init__.py
ezm_agent/agent.py
ezm_agent/logger.py
ezm_agent/profiler.py
ezm_agent/sign.py
ezm_agent/websocket.py
ezm_agent-0.0.5.dist-info/LICENSE
ezm_agent-0.0.5.dist-info/METADATA
ezm_agent-0.0.5.dist-info/WHEEL
ezm_agent-0.0.5.dist-info/top_level.txt
ezm_agent-0.0.5.dist-info/RECORD
