Metadata-Version: 2.1
Name: ezm_agent
Version: 0.0.5
Summary: A Easy Monitor Agent for Python
Author-email: noodanee <noodanee@qq.com>
Classifier: Programming Language :: Python :: 3
Classifier: License :: OSI Approved :: MIT License
Classifier: Operating System :: OS Independent
Requires-Python: >=3.8
License-File: LICENSE
Requires-Dist: psutil
Requires-Dist: rpyc
Requires-Dist: websockets
